Metadata-Version: 1.1
Name: connect-snowflake
Version: 0.1.0
Summary: A Python package to connect snowflake
Home-page: https://github.com/shuds13/pyexample
Author: Abhishek
Author-email: UNKNOWN
License: BSD 2-clause
Platform: UNKNOWN
Classifier: Development Status :: 1 - Planning
Classifier: Intended Audience :: Science/Research
Classifier: License :: OSI Approved :: BSD License
Classifier: Operating System :: POSIX :: Linux
Classifier: Programming Language :: Python :: 3.6
Classifier: Programming Language :: Python :: 3.7
Classifier: Programming Language :: Python :: 3.8
